README.md
setup.cfg
setup.py
src/__init__.py
src/ytspider.py
src/utils/__init__.py
src/utils/client.py
src/utils/context.py
src/utils/decorator.py
src/utils/handler.py
src/utils/playback_context.py
src/utils/request.py
src/utils/signals_info.py
ytspider.egg-info/PKG-INFO
ytspider.egg-info/SOURCES.txt
ytspider.egg-info/dependency_links.txt
ytspider.egg-info/requires.txt
ytspider.egg-info/top_level.txt