Metadata-Version: 2.1
Name: ytspider
Version: 0.0.0.5
Summary: YouTube scraper, videos, channels, playlists, comments and transcriptions
Home-page: https://github.com/zementalist
Author: Zeyad Khalid
Author-email: zeyadpro99@gmail.com
Maintainer-email: zeyad.khalid@must.edu.eg
License: MIT
Keywords: web crawling youtube scraping api
Platform: UNKNOWN
